src/data_mem.v
module data_mem(
    input clk,
    input mem_read,
    input mem_write,
    input [31:0] addr,
    input [31:0] write_data,
    output [31:0] read_data
);

    reg [31:0] memory [0:1023];

    always @(posedge clk) begin
        if (mem_write) begin
            memory[addr[11:2]] <= write_data;
        end
    end

    assign read_data = (mem_read) ? memory[addr[11:2]] : 32'b0;

endmodule

src/alu.v
module alu (
    input [31:0] a,
    input [31:0] b,
    input [3:0] opcode,
    output reg [31:0] result,
    output wire zero 

);
    always @(*) begin
        case (opcode)
            4'b0000: result = a + b; //add
            4'b0001: result = a - b; //sub
            4'b0010: result = a & b; //and
            4'b0011: result = a | b; //or
            
            //discarded for now
            /*4'b0100: result = a ^ b; //xor
            4'b0101: result = ~(a | b); //nor
            4'b0110: result = ~(a & b); //nand
            4'b0111: result = (a<b) ? 32'd1 : 32'd0; //set less than
            4'b1000: result = a << b[4:0]; //shift left logical
            4'b1001: result = a >> b[4:0]; //shift right logical*/
            default: result = 32'b0; 
        endcase
    end

    assign zero = (result == 32'b0);

endmodule

src/register_file.v
module reg_file (
    input clk,
    input rst,
    input rg_write_en,// Write Enable: only write if this is 1
    input [4:0] rg_des_addr,// Destination register index (0-31)
    input [4:0] rg_sr1_addr,// Source 1 register index (0-31)
    input [4:0] rg_sr2_addr,// Source 2 register index (0-31)
    input [31:0] rg_des_data,// Data to be written
    output [31:0] rg_sr1_data,// Data read from Source 1
    output [31:0] rg_sr2_data// Data read from Source 2
);
reg [31:0] registers [31:0];
integer i;

assign rg_sr1_data = (rg_sr1_addr == 5'b0) ? 32'b0 : registers[rg_sr1_addr];
assign rg_sr2_data = (rg_sr2_addr == 5'b0) ? 32'b0 : registers[rg_sr2_addr];

always @(posedge clk) begin
    if(rst) begin
        for(i=0;  i<32; i=i+1)begin
            registers[i] <=32'b0;
        end
    end 
    else if (rg_write_en && (rg_des_addr!=5'b0)) begin
            registers[rg_des_addr] <= rg_des_data;
    end
end



endmodule

src/control_unit.v
module control_unit(
    input [6:0] opcode,
    output reg branch,
    output reg reg_write,
    output reg alu_src,
    output reg mem_read,
    output reg mem_write,
    output reg mem_to_reg,
    output reg [1:0] alu_op

);
always @(*) begin
    reg_write  = 0;
    alu_src    = 0;
    mem_read   = 0;
    mem_write  = 0;
    mem_to_reg = 0;
    branch=0;
    alu_op     = 2'b00;
    case(opcode)
        7'b0110011: begin //R-type ADD
            reg_write  = 1;
            alu_src    = 0;
            alu_op     = 2'b10;
        end
        7'b0010011: begin //I-type ADDI
            reg_write  = 1;
            alu_src    = 1;
            alu_op     = 2'b00; //force add
        end
        7'b0000011: begin // Load (LW)
            reg_write  = 1;
            mem_read   = 1;
            mem_to_reg = 1; 
            alu_src    = 1;
            mem_write = 0;
            alu_op     = 2'b00;
        end

        7'b0100011: begin // Store (SW)
            reg_write  = 0;
            mem_write   = 1;
            mem_read = 0;
            mem_to_reg = 0; 
            alu_src    = 1;
            alu_op     = 2'b00;
        end
        7'b1100011: begin // BEQ
            reg_write  = 0;
            alu_src    = 0;
            mem_read   = 0;
            mem_write  = 0;
            mem_to_reg = 0;
            branch     = 1;
            alu_op     = 2'b01; // subtract rs1 - rs2
        end

        
        default: begin
            
        end
        endcase
    end

endmodule

src/instruction_mem.v
module instruction_mem (
    input  [31:0] addr, //From PC
    output [31:0] instruction //To Control/Reg
);

    reg [31:0] memory [0:1023];
    
    initial begin
        $readmemh("sample_program.hex", memory);
    end

    assign instruction = memory[addr >> 2]; //converts from the address to the word index, 32 bit so each is 4 bytes

endmodule

src/pc.v
module pc(
    input clk,
    input reset,
    input [31:0] pc_in,
    output reg [31:0] pc_out
);

always @(posedge clk) begin
    if (reset) begin
        pc_out <= 32'b0;
    end else begin
        pc_out <= pc_in;
    end
end
endmodule

src/riscv_top.v
module riscv_top(
    input clk,
    input rst
);

    //IF stage wires
    wire [31:0] if_instr;
    wire [31:0] pc_out;
    wire [31:0] if_pc_plus4;

    //IF/ID pipeline register
    reg [31:0] if_id_pc;
    reg [31:0] if_id_pc_plus4;
    reg [31:0] if_id_instr;

    //ID stage wires decoded from if_id_instr
    wire [6:0]  id_opcode = if_id_instr[6:0];
    wire [4:0]  id_rd     = if_id_instr[11:7];
    wire [2:0]  id_funct3 = if_id_instr[14:12];
    wire [4:0]  id_rs1    = if_id_instr[19:15];
    wire [4:0]  id_rs2    = if_id_instr[24:20];
    wire [6:0]  id_funct7 = if_id_instr[31:25];

    wire [31:0] id_reg_data1, id_reg_data2;
    wire [31:0] id_imm_ext;
    wire        id_reg_write, id_alu_src, id_mem_read, id_mem_write, id_mem_to_reg, id_branch;
    wire [1:0]  id_alu_op;

    //ID/EX pipeline register
    reg [31:0] id_ex_pc;
    reg [31:0] id_ex_pc_plus4;
    reg [31:0] id_ex_reg_data1;
    reg [31:0] id_ex_reg_data2;
    reg [31:0] id_ex_imm_ext;
    reg [4:0]  id_ex_rd;
    reg [4:0]  id_ex_rs1;
    reg [4:0]  id_ex_rs2;
    reg [2:0]  id_ex_funct3;
    reg [6:0]  id_ex_funct7;
    reg        id_ex_reg_write;
    reg        id_ex_alu_src;
    reg        id_ex_mem_read;
    reg        id_ex_mem_write;
    reg        id_ex_mem_to_reg;
    reg        id_ex_branch;
    reg [1:0]  id_ex_alu_op;

    //EX stage wires
    reg  [3:0]  ex_alu_control;
    wire [31:0] ex_alu_a;
    wire [31:0] ex_alu_b_reg;
    wire [31:0] ex_alu_src2;
    wire [31:0] ex_alu_result;
    wire        ex_zero;
    wire [31:0] ex_branch_target;

    //EX/MEM pipeline register
    reg [31:0] ex_mem_pc_plus4;
    reg [31:0] ex_mem_branch_target;
    reg [31:0] ex_mem_alu_result;
    reg        ex_mem_zero;
    reg [31:0] ex_mem_reg_data2;
    reg [4:0]  ex_mem_rd;
    reg        ex_mem_reg_write;
    reg        ex_mem_mem_read;
    reg        ex_mem_mem_write;
    reg        ex_mem_mem_to_reg;
    reg        ex_mem_branch;

    //MEM stage wires
    wire [31:0] mem_read_data;

    //MEM/WB pipeline register
    reg [31:0] mem_wb_alu_result;
    reg [31:0] mem_wb_read_data;
    reg [4:0]  mem_wb_rd;
    reg        mem_wb_reg_write;
    reg        mem_wb_mem_to_reg;

    //WB stage wire
    wire [31:0] wb_write_data;

    //detect branch taken while BEQ is still in EX (early detection)
    //using ex_mem signals would be 1 cycle too late — the wrong instruction
    //would already be latched into ID/EX and propagate one more stage
    wire branch_taken = id_ex_branch && ex_zero;
    wire flush        = branch_taken;

    assign if_pc_plus4 = pc_out + 32'd4;
    //use ex_branch_target directly — it's valid while BEQ is in EX
    wire [31:0] pc_next = branch_taken ? ex_branch_target : if_pc_plus4;

    //load-use hazard: stall if LW in EX and dependent instruction in ID
    wire stall = id_ex_mem_read &&
                 (id_ex_rd != 5'b0) &&
                 ((id_ex_rd == id_rs1) || (id_ex_rd == id_rs2));

    //hold PC when stalling
    wire [31:0] pc_in_mux = stall ? pc_out : pc_next;

    pc my_pc (
        .clk(clk),
        .reset(rst),
        .pc_in(pc_in_mux),
        .pc_out(pc_out)
    );

    instruction_mem my_imem (
        .addr(pc_out),
        .instruction(if_instr)
    );

    //IF/ID register: flush on taken branch, hold on stall
    always @(posedge clk) begin
        if (rst || flush) begin
            if_id_pc       <= 32'b0;
            if_id_pc_plus4 <= 32'b0;
            if_id_instr    <= 32'b0;
        end else if (!stall) begin
            if_id_pc       <= pc_out;
            if_id_pc_plus4 <= if_pc_plus4;
            if_id_instr    <= if_instr;
        end
    end

    //immediate generation
    wire [31:0] i_ext = {{20{if_id_instr[31]}}, if_id_instr[31:20]};
    wire [31:0] s_ext = {{20{if_id_instr[31]}}, if_id_instr[31:25], if_id_instr[11:7]};
    wire [31:0] b_ext = {{19{if_id_instr[31]}}, if_id_instr[31], if_id_instr[7],
                          if_id_instr[30:25], if_id_instr[11:8], 1'b0};
    assign id_imm_ext = (id_opcode == 7'b0000011 || id_opcode == 7'b0010011) ? i_ext :
                        (id_opcode == 7'b0100011) ? s_ext :
                        (id_opcode == 7'b1100011) ? b_ext :
                        32'b0;

    control_unit my_cu (
        .opcode(id_opcode),
        .reg_write(id_reg_write),
        .alu_src(id_alu_src),
        .mem_read(id_mem_read),
        .mem_write(id_mem_write),
        .mem_to_reg(id_mem_to_reg),
        .alu_op(id_alu_op),
        .branch(id_branch)
    );

    //register reads happen in ID, writeback comes from MEM/WB
    reg_file my_regfile (
        .clk(clk),
        .rst(rst),
        .rg_write_en(mem_wb_reg_write),
        .rg_des_addr(mem_wb_rd),
        .rg_sr1_addr(id_rs1),
        .rg_sr2_addr(id_rs2),
        .rg_des_data(wb_write_data),
        .rg_sr1_data(id_reg_data1),
        .rg_sr2_data(id_reg_data2)
    );

    //ID/EX register: inject NOP bubble on stall or flush
    always @(posedge clk) begin
        if (rst || stall || flush) begin
            id_ex_pc         <= 32'b0;
            id_ex_pc_plus4   <= 32'b0;
            id_ex_reg_data1  <= 32'b0;
            id_ex_reg_data2  <= 32'b0;
            id_ex_imm_ext    <= 32'b0;
            id_ex_rd         <= 5'b0;
            id_ex_rs1        <= 5'b0;
            id_ex_rs2        <= 5'b0;
            id_ex_funct3     <= 3'b0;
            id_ex_funct7     <= 7'b0;
            id_ex_reg_write  <= 1'b0;
            id_ex_alu_src    <= 1'b0;
            id_ex_mem_read   <= 1'b0;
            id_ex_mem_write  <= 1'b0;
            id_ex_mem_to_reg <= 1'b0;
            id_ex_branch     <= 1'b0;
            id_ex_alu_op     <= 2'b0;
        end else begin
            id_ex_pc         <= if_id_pc;
            id_ex_pc_plus4   <= if_id_pc_plus4;
            id_ex_reg_data1  <= id_reg_data1;
            id_ex_reg_data2  <= id_reg_data2;
            id_ex_imm_ext    <= id_imm_ext;
            id_ex_rd         <= id_rd;
            id_ex_rs1        <= id_rs1;
            id_ex_rs2        <= id_rs2;
            id_ex_funct3     <= id_funct3;
            id_ex_funct7     <= id_funct7;
            id_ex_reg_write  <= id_reg_write;
            id_ex_alu_src    <= id_alu_src;
            id_ex_mem_read   <= id_mem_read;
            id_ex_mem_write  <= id_mem_write;
            id_ex_mem_to_reg <= id_mem_to_reg;
            id_ex_branch     <= id_branch;
            id_ex_alu_op     <= id_alu_op;
        end
    end

    //ALU control derived from alu_op + funct3/funct7
    always @(*) begin
        case (id_ex_alu_op)
            2'b00: ex_alu_control = 4'b0000; //ADD for load/store/ADDI
            2'b01: ex_alu_control = 4'b0001; //SUB for branch comparison
            2'b10: begin
                case (id_ex_funct3)
                    3'b000:  ex_alu_control = id_ex_funct7[5] ? 4'b0001 : 4'b0000; //SUB or ADD
                    3'b111:  ex_alu_control = 4'b0010; //AND
                    3'b110:  ex_alu_control = 4'b0011; //OR
                    default: ex_alu_control = 4'b0000;
                endcase
            end
            default: ex_alu_control = 4'b0000;
        endcase
    end

    //forwarding unit: select correct ALU source to resolve RAW hazards
    reg [1:0] forward_a, forward_b;
    always @(*) begin
        //EX/MEM forwarding (higher priority)
        if (ex_mem_reg_write && (ex_mem_rd != 5'b0) && (ex_mem_rd == id_ex_rs1))
            forward_a = 2'b10;
        //MEM/WB forwarding
        else if (mem_wb_reg_write && (mem_wb_rd != 5'b0) && (mem_wb_rd == id_ex_rs1))
            forward_a = 2'b01;
        else
            forward_a = 2'b00;

        if (ex_mem_reg_write && (ex_mem_rd != 5'b0) && (ex_mem_rd == id_ex_rs2))
            forward_b = 2'b10;
        else if (mem_wb_reg_write && (mem_wb_rd != 5'b0) && (mem_wb_rd == id_ex_rs2))
            forward_b = 2'b01;
        else
            forward_b = 2'b00;
    end

    assign ex_alu_a     = (forward_a == 2'b10) ? ex_mem_alu_result :
                          (forward_a == 2'b01) ? wb_write_data :
                          id_ex_reg_data1;

    assign ex_alu_b_reg = (forward_b == 2'b10) ? ex_mem_alu_result :
                          (forward_b == 2'b01) ? wb_write_data :
                          id_ex_reg_data2;

    assign ex_alu_src2     = id_ex_alu_src ? id_ex_imm_ext : ex_alu_b_reg;
    assign ex_branch_target = id_ex_pc + id_ex_imm_ext;

    alu my_alu (
        .opcode(ex_alu_control),
        .a(ex_alu_a),
        .b(ex_alu_src2),
        .result(ex_alu_result),
        .zero(ex_zero)
    );

    //EX/MEM register
    always @(posedge clk) begin
        if (rst) begin
            ex_mem_pc_plus4      <= 32'b0;
            ex_mem_branch_target <= 32'b0;
            ex_mem_alu_result    <= 32'b0;
            ex_mem_zero          <= 1'b0;
            ex_mem_reg_data2     <= 32'b0;
            ex_mem_rd            <= 5'b0;
            ex_mem_reg_write     <= 1'b0;
            ex_mem_mem_read      <= 1'b0;
            ex_mem_mem_write     <= 1'b0;
            ex_mem_mem_to_reg    <= 1'b0;
            ex_mem_branch        <= 1'b0;
        end else begin
            ex_mem_pc_plus4      <= id_ex_pc_plus4;
            ex_mem_branch_target <= ex_branch_target;
            ex_mem_alu_result    <= ex_alu_result;
            ex_mem_zero          <= ex_zero;
            ex_mem_reg_data2     <= ex_alu_b_reg; //forwarded rs2 for SW
            ex_mem_rd            <= id_ex_rd;
            ex_mem_reg_write     <= id_ex_reg_write;
            ex_mem_mem_read      <= id_ex_mem_read;
            ex_mem_mem_write     <= id_ex_mem_write;
            ex_mem_mem_to_reg    <= id_ex_mem_to_reg;
            ex_mem_branch        <= id_ex_branch;
        end
    end

    data_mem my_dmem (
        .clk(clk),
        .mem_read(ex_mem_mem_read),
        .mem_write(ex_mem_mem_write),
        .addr(ex_mem_alu_result),
        .write_data(ex_mem_reg_data2),
        .read_data(mem_read_data)
    );

    //MEM/WB register
    always @(posedge clk) begin
        if (rst) begin
            mem_wb_alu_result  <= 32'b0;
            mem_wb_read_data   <= 32'b0;
            mem_wb_rd          <= 5'b0;
            mem_wb_reg_write   <= 1'b0;
            mem_wb_mem_to_reg  <= 1'b0;
        end else begin
            mem_wb_alu_result  <= ex_mem_alu_result;
            mem_wb_read_data   <= mem_read_data;
            mem_wb_rd          <= ex_mem_rd;
            mem_wb_reg_write   <= ex_mem_reg_write;
            mem_wb_mem_to_reg  <= ex_mem_mem_to_reg;
        end
    end

    assign wb_write_data = mem_wb_mem_to_reg ? mem_wb_read_data : mem_wb_alu_result;

endmodule

test/top_tb.v
`timescale 1ns/1ps

module riscv_top_tb();
    reg clk;
    reg rst;

    riscv_top dut (
        .clk(clk),
        .rst(rst)
    );

    always #5 clk = ~clk;

    initial begin
        $dumpfile("riscv_processor.vcd");
        $dumpvars(0, riscv_top_tb);

        clk = 0;
        rst = 1;
        #15;
        rst = 0;

        // pipeline with flush needs ~15 cycles; 200ns gives safe margin
        #200;

        if (dut.my_regfile.registers[1] !== 32'd5) begin
            $display("FAIL: x1 expected 5, got %0d", dut.my_regfile.registers[1]);
            $finish;
        end

        if (dut.my_regfile.registers[2] !== 32'd5) begin
            $display("FAIL: x2 expected 5, got %0d", dut.my_regfile.registers[2]);
            $finish;
        end

        if (dut.my_regfile.registers[3] !== 32'd0) begin
            $display("FAIL: x3 expected 0 because BEQ should skip ADDI, got %0d", dut.my_regfile.registers[3]);
            $finish;
        end

        if (dut.my_regfile.registers[4] !== 32'd42) begin
            $display("FAIL: x4 expected 42, got %0d", dut.my_regfile.registers[4]);
            $finish;
        end

        $display("PASS: BEQ skipped the ADDI to x3 and executed the ADDI to x4.");
        $finish;
    end
endmodule

riscv_processor.vcd
$date
	Wed Apr 29 22:20:31 2026
$end
$version
	Icarus Verilog
$end
$timescale
	1ps
$end
$scope module riscv_top_tb $end
$var reg 1 ! clk $end
$var reg 1 " rst $end
$scope module dut $end
$var wire 1 # branch_taken $end
$var wire 1 ! clk $end
$var wire 1 $ flush $end
$var wire 1 " rst $end
$var wire 1 % stall $end
$var wire 32 & wb_write_data [31:0] $end
$var wire 32 ' s_ext [31:0] $end
$var wire 32 ( pc_out [31:0] $end
$var wire 32 ) pc_next [31:0] $end
$var wire 32 * pc_in_mux [31:0] $end
$var wire 32 + mem_read_data [31:0] $end
$var wire 32 , if_pc_plus4 [31:0] $end
$var wire 32 - if_instr [31:0] $end
$var wire 5 . id_rs2 [4:0] $end
$var wire 5 / id_rs1 [4:0] $end
$var wire 1 0 id_reg_write $end
$var wire 32 1 id_reg_data2 [31:0] $end
$var wire 32 2 id_reg_data1 [31:0] $end
$var wire 5 3 id_rd [4:0] $end
$var wire 7 4 id_opcode [6:0] $end
$var wire 1 5 id_mem_write $end
$var wire 1 6 id_mem_to_reg $end
$var wire 1 7 id_mem_read $end
$var wire 32 8 id_imm_ext [31:0] $end
$var wire 7 9 id_funct7 [6:0] $end
$var wire 3 : id_funct3 [2:0] $end
$var wire 1 ; id_branch $end
$var wire 1 < id_alu_src $end
$var wire 2 = id_alu_op [1:0] $end
$var wire 32 > i_ext [31:0] $end
$var wire 1 ? ex_zero $end
$var wire 32 @ ex_branch_target [31:0] $end
$var wire 32 A ex_alu_src2 [31:0] $end
$var wire 32 B ex_alu_result [31:0] $end
$var wire 32 C ex_alu_b_reg [31:0] $end
$var wire 32 D ex_alu_a [31:0] $end
$var wire 32 E b_ext [31:0] $end
$var reg 4 F ex_alu_control [3:0] $end
$var reg 32 G ex_mem_alu_result [31:0] $end
$var reg 1 H ex_mem_branch $end
$var reg 32 I ex_mem_branch_target [31:0] $end
$var reg 1 J ex_mem_mem_read $end
$var reg 1 K ex_mem_mem_to_reg $end
$var reg 1 L ex_mem_mem_write $end
$var reg 32 M ex_mem_pc_plus4 [31:0] $end
$var reg 5 N ex_mem_rd [4:0] $end
$var reg 32 O ex_mem_reg_data2 [31:0] $end
$var reg 1 P ex_mem_reg_write $end
$var reg 1 Q ex_mem_zero $end
$var reg 2 R forward_a [1:0] $end
$var reg 2 S forward_b [1:0] $end
$var reg 2 T id_ex_alu_op [1:0] $end
$var reg 1 U id_ex_alu_src $end
$var reg 1 V id_ex_branch $end
$var reg 3 W id_ex_funct3 [2:0] $end
$var reg 7 X id_ex_funct7 [6:0] $end
$var reg 32 Y id_ex_imm_ext [31:0] $end
$var reg 1 Z id_ex_mem_read $end
$var reg 1 [ id_ex_mem_to_reg $end
$var reg 1 \ id_ex_mem_write $end
$var reg 32 ] id_ex_pc [31:0] $end
$var reg 32 ^ id_ex_pc_plus4 [31:0] $end
$var reg 5 _ id_ex_rd [4:0] $end
$var reg 32 ` id_ex_reg_data1 [31:0] $end
$var reg 32 a id_ex_reg_data2 [31:0] $end
$var reg 1 b id_ex_reg_write $end
$var reg 5 c id_ex_rs1 [4:0] $end
$var reg 5 d id_ex_rs2 [4:0] $end
$var reg 32 e if_id_instr [31:0] $end
$var reg 32 f if_id_pc [31:0] $end
$var reg 32 g if_id_pc_plus4 [31:0] $end
$var reg 32 h mem_wb_alu_result [31:0] $end
$var reg 1 i mem_wb_mem_to_reg $end
$var reg 5 j mem_wb_rd [4:0] $end
$var reg 32 k mem_wb_read_data [31:0] $end
$var reg 1 l mem_wb_reg_write $end
$scope module my_alu $end
$var wire 32 m a [31:0] $end
$var wire 32 n b [31:0] $end
$var wire 4 o opcode [3:0] $end
$var wire 1 ? zero $end
$var reg 32 p result [31:0] $end
$upscope $end
$scope module my_cu $end
$var wire 7 q opcode [6:0] $end
$var reg 2 r alu_op [1:0] $end
$var reg 1 < alu_src $end
$var reg 1 ; branch $end
$var reg 1 7 mem_read $end
$var reg 1 6 mem_to_reg $end
$var reg 1 5 mem_write $end
$var reg 1 0 reg_write $end
$upscope $end
$scope module my_dmem $end
$var wire 32 s addr [31:0] $end
$var wire 1 ! clk $end
$var wire 1 J mem_read $end
$var wire 1 L mem_write $end
$var wire 32 t write_data [31:0] $end
$var wire 32 u read_data [31:0] $end
$upscope $end
$scope module my_imem $end
$var wire 32 v instruction [31:0] $end
$var wire 32 w addr [31:0] $end
$upscope $end
$scope module my_pc $end
$var wire 1 ! clk $end
$var wire 32 x pc_in [31:0] $end
$var wire 1 " reset $end
$var reg 32 y pc_out [31:0] $end
$upscope $end
$scope module my_regfile $end
$var wire 1 ! clk $end
$var wire 5 z rg_des_addr [4:0] $end
$var wire 32 { rg_des_data [31:0] $end
$var wire 5 | rg_sr1_addr [4:0] $end
$var wire 5 } rg_sr2_addr [4:0] $end
$var wire 1 l rg_write_en $end
$var wire 1 " rst $end
$var wire 32 ~ rg_sr2_data [31:0] $end
$var wire 32 !" rg_sr1_data [31:0] $end
$var integer 32 "" i [31:0] $end
$upscope $end
$upscope $end
$upscope $end
$enddefinitions $end
$comment Show the parameter values. $end
$dumpall
$end
#0
$dumpvars
bx ""
bx !"
bx ~
bx }
bx |
bx {
bx z
bx y
bx x
bx w
bx v
bx u
bx t
bx s
bx r
bx q
bx p
bx o
bx n
bx m
xl
bx k
bx j
xi
bx h
bx g
bx f
bx e
bx d
bx c
xb
bx a
bx `
bx _
bx ^
bx ]
x\
x[
xZ
bx Y
bx X
bx W
xV
xU
bx T
bx S
bx R
xQ
xP
bx O
bx N
bx M
xL
xK
xJ
bx I
xH
bx G
bx F
bx0 E
bx D
bx C
bx B
bx A
bx @
x?
bx >
bx =
x<
x;
bx :
bx 9
bx 8
x7
x6
x5
bx 4
bx 3
bx 2
bx 1
x0
bx /
bx .
bx -
bx ,
bx +
bx *
bx )
bx (
bx '
bx &
x%
x$
x#
1"
0!
$end
#5000
1?
b0 B
b0 p
b0 8
b0 E
b0 A
b0 n
b10100000000000010010011 -
b10100000000000010010011 v
b0 =
b0 r
0;
06
05
07
0<
00
b0 2
b0 !"
b0 1
b0 ~
b0 >
b0 '
0%
b0 C
b0 D
b0 m
b100 *
b100 x
b0 4
b0 q
b0 3
b0 :
b0 /
b0 |
b0 .
b0 }
b0 9
0$
0#
b0 F
b0 o
b100 )
b0 +
b0 u
b0 S
b0 R
b0 &
b0 {
b100 ,
b0 (
b0 w
b0 y
b0 e
b0 g
b0 f
b0 T
0V
0[
0\
0Z
0U
0b
b0 X
b0 W
b0 d
b0 c
b0 _
b0 @
b0 Y
b0 a
b0 `
b0 ^
b0 ]
0H
0K
0L
0J
0P
b0 N
b0 O
b0 t
0Q
b0 G
b0 s
b0 I
b0 M
0i
0l
b0 j
b0 z
b0 k
b0 h
b100000 ""
1!
#10000
0!
#15000
b101 8
b100000000000 E
1<
10
b101 >
b1 '
b10100000000000100010011 -
b10100000000000100010011 v
b1000 *
b1000 x
b10011 4
b10011 q
b1 3
b101 .
b101 }
b1000 )
1Q
b10100000000000010010011 e
b100 g
b1000 ,
b100 (
b100 w
b100 y
1!
0"
#20000
0!
#25000
b10 E
b1000001000010001100011 -
b1000001000010001100011 v
b1100 *
b1100 x
b10 '
0?
b101 B
b101 p
b1100 )
b10 3
b101 A
b101 n
b1100 ,
b1000 (
b1000 w
b1000 y
b10100000000000100010011 e
b1000 g
b100 f
1U
1b
b101 d
b1 _
b101 @
b101 Y
b100 ^
1!
#30000
0!
#35000
b1000 8
b1000 E
b1 =
b1 r
1;
0<
00
b10 >
b1000 '
b110001100000000000110010011 -
b110001100000000000110010011 v
b10000 *
b10000 x
b1100011 4
b1100011 q
b1000 3
b1 /
b1 |
b10 .
b10 }
b10000 )
1P
b1 N
0Q
b101 G
b101 s
b101 I
b100 M
b10 _
b1000 ^
b1001 @
b100 ]
b1000001000010001100011 e
b1100 g
b1000 f
b10000 ,
b1100 (
b1100 w
b1100 y
1!
#40000
0!
#45000
b1100011 8
b100001100010 E
1$
1#
b101 D
b101 m
b10101000000000001000010011 -
b10101000000000001000010011 v
b10000 *
b10000 x
1<
10
b0 =
b0 r
0;
b1100011 >
b1100011 '
1?
b0 B
b0 p
b101 C
b10000 )
b10011 4
b10011 q
b11 3
b0 /
b0 |
b11 .
b11 }
b11 9
b1 F
b1 o
b101 A
b101 n
b10 S
b1 R
b101 &
b101 {
b10100 ,
b10000 (
b10000 w
b10000 y
b110001100000000000110010011 e
b10000 g
b1100 f
b1 T
1V
0U
0b
b10 d
b1 c
b1000 _
b1000 Y
b1100 ^
b10000 @
b1000 ]
b10 N
b1001 I
b1000 M
1l
b1 j
b1 z
b101 h
1!
#50000
0!
#55000
b0 D
b0 m
b0 8
b0 E
b0 A
b0 n
1?
b0 B
b0 p
b10100 *
b10100 x
0<
00
b0 >
b0 '
b0 C
b0 F
b0 o
0$
0#
b0 S
b0 R
b10100 )
b0 4
b0 q
b0 3
b0 .
b0 }
b0 9
b10 j
b10 z
1H
0P
b1000 N
b101 O
b101 t
1Q
b0 G
b0 s
b10000 I
b1100 M
b0 T
0V
b0 d
b0 c
b0 _
b0 Y
b0 ^
b0 @
b0 ]
b0 e
b0 g
b0 f
1!
#60000
0!
#65000
b101010 8
b100100 E
bx -
bx v
b11000 *
b11000 x
1<
10
b101010 >
b100100 '
b11000 )
b10011 4
b10011 q
b100 3
b1010 .
b1010 }
b1 9
b0 &
b0 {
b11000 ,
b10100 (
b10100 w
b10100 y
b10101000000000001000010011 e
b10100 g
b10000 f
0H
b0 N
b0 O
b0 t
b0 I
b0 M
0l
b1000 j
b1000 z
b0 h
1!
#70000
0!
#75000
bx 8
bx0 E
0?
b101010 B
b101010 p
0<
00
bx 2
bx !"
bx 1
bx ~
bx >
bx '
b11100 *
b11100 x
b101010 A
b101010 n
bx 4
bx q
bx 3
bx :
bx /
bx |
bx .
bx }
bx 9
b11100 )
b0 j
b0 z
1U
1b
b1 X
b1010 d
b100 _
b101010 Y
b10100 ^
b111010 @
b10000 ]
bx e
b11000 g
b10100 f
b11100 ,
b11000 (
b11000 w
b11000 y
1!
#80000
0!
#85000
b100000 *
b100000 x
x?
bx B
bx p
bx C
bx D
bx m
b100000 )
bx A
bx n
b100000 ,
b11100 (
b11100 w
b11100 y
b11100 g
b11000 f
0U
0b
bx X
bx W
bx d
bx c
bx _
bx Y
bx a
bx `
b11000 ^
bx @
b10100 ]
1P
b100 N
0Q
b101010 G
b101010 s
b111010 I
b10100 M
1!
#90000
0!
#95000
b100100 *
b100100 x
b101010 &
b101010 {
b100100 )
1l
b100 j
b100 z
b101010 h
0P
bx N
bx O
bx t
xQ
bx G
bx s
bx I
b11000 M
b11100 ^
b11000 ]
b100000 g
b11100 f
b100100 ,
b100000 (
b100000 w
b100000 y
1!
#100000
0!
#105000
b101000 *
b101000 x
b101000 )
bx &
bx {
b101000 ,
b100100 (
b100100 w
b100100 y
b100100 g
b100000 f
b100000 ^
b11100 ]
b11100 M
0l
bx j
bx z
bx h
1!
#110000
0!
#115000
b101100 *
b101100 x
b101100 )
b100000 M
b100100 ^
b100000 ]
b101000 g
b100100 f
b101100 ,
b101000 (
b101000 w
b101000 y
1!
#120000
0!
#125000
b110000 *
b110000 x
b110000 )
b110000 ,
b101100 (
b101100 w
b101100 y
b101100 g
b101000 f
b101000 ^
b100100 ]
b100100 M
1!
#130000
0!
#135000
b110100 *
b110100 x
b110100 )
b101000 M
b101100 ^
b101000 ]
b110000 g
b101100 f
b110100 ,
b110000 (
b110000 w
b110000 y
1!
#140000
0!
#145000
b111000 *
b111000 x
b111000 )
b111000 ,
b110100 (
b110100 w
b110100 y
b110100 g
b110000 f
b110000 ^
b101100 ]
b101100 M
1!
#150000
0!
#155000
b111100 *
b111100 x
b111100 )
b110000 M
b110100 ^
b110000 ]
b111000 g
b110100 f
b111100 ,
b111000 (
b111000 w
b111000 y
1!
#160000
0!
#165000
b1000000 *
b1000000 x
b1000000 )
b1000000 ,
b111100 (
b111100 w
b111100 y
b111100 g
b111000 f
b111000 ^
b110100 ]
b110100 M
1!
#170000
0!
#175000
b1000100 *
b1000100 x
b1000100 )
b111000 M
b111100 ^
b111000 ]
b1000000 g
b111100 f
b1000100 ,
b1000000 (
b1000000 w
b1000000 y
1!
#180000
0!
#185000
b1001000 *
b1001000 x
b1001000 )
b1001000 ,
b1000100 (
b1000100 w
b1000100 y
b1000100 g
b1000000 f
b1000000 ^
b111100 ]
b111100 M
1!
#190000
0!
#195000
b1001100 *
b1001100 x
b1001100 )
b1000000 M
b1000100 ^
b1000000 ]
b1001000 g
b1000100 f
b1001100 ,
b1001000 (
b1001000 w
b1001000 y
1!
#200000
0!
#205000
b1010000 *
b1010000 x
b1010000 )
b1010000 ,
b1001100 (
b1001100 w
b1001100 y
b1001100 g
b1001000 f
b1001000 ^
b1000100 ]
b1000100 M
1!
#210000
0!
#215000
b1010100 *
b1010100 x
b1010100 )
b1001000 M
b1001100 ^
b1001000 ]
b1010000 g
b1001100 f
b1010100 ,
b1010000 (
b1010000 w
b1010000 y
1!
