src/data_mem.v
module data_mem(
    input clk,
    input mem_read,
    input mem_write,
    input [31:0] addr,
    input [31:0] write_data,
    output [31:0] read_data
);

    reg [31:0] memory [0:1023];

    always @(posedge clk) begin
        if (mem_write) begin
            memory[addr[11:2]] <= write_data;
        end
    end

    assign read_data = (mem_read) ? memory[addr[11:2]] : 32'b0;

endmodule

src/alu.v
module alu (
    input [31:0] a,
    input [31:0] b,
    input [3:0] opcode,
    output reg [31:0] result,
    output wire zero 

);
    always @(*) begin
        case (opcode)
            4'b0000: result = a + b; //add
            4'b0001: result = a - b; //sub
            4'b0010: result = a & b; //and
            4'b0011: result = a | b; //or
            
            //discarded for now
            /*4'b0100: result = a ^ b; //xor
            4'b0101: result = ~(a | b); //nor
            4'b0110: result = ~(a & b); //nand
            4'b0111: result = (a<b) ? 32'd1 : 32'd0; //set less than
            4'b1000: result = a << b[4:0]; //shift left logical
            4'b1001: result = a >> b[4:0]; //shift right logical*/
            default: result = 32'b0; 
        endcase
    end

    assign zero = (result == 32'b0);

endmodule

src/register_file.v
module reg_file (
    input clk,
    input rst,
    input rg_write_en,// Write Enable: only write if this is 1
    input [4:0] rg_des_addr,// Destination register index (0-31)
    input [4:0] rg_sr1_addr,// Source 1 register index (0-31)
    input [4:0] rg_sr2_addr,// Source 2 register index (0-31)
    input [31:0] rg_des_data,// Data to be written
    output [31:0] rg_sr1_data,// Data read from Source 1
    output [31:0] rg_sr2_data// Data read from Source 2
);
reg [31:0] registers [31:0];
integer i;

assign rg_sr1_data = (rg_sr1_addr == 5'b0) ? 32'b0 : registers[rg_sr1_addr];
assign rg_sr2_data = (rg_sr2_addr == 5'b0) ? 32'b0 : registers[rg_sr2_addr];

always @(posedge clk) begin
    if(rst) begin
        for(i=0;  i<32; i=i+1)begin
            registers[i] <=32'b0;
        end
    end 
    else if (rg_write_en && (rg_des_addr!=5'b0)) begin
            registers[rg_des_addr] <= rg_des_data;
    end
end



endmodule

src/control_unit.v
module control_unit(
    input [6:0] opcode,
    output reg branch,
    output reg reg_write,
    output reg alu_src,
    output reg mem_read,
    output reg mem_write,
    output reg mem_to_reg,
    output reg [1:0] alu_op

);
always @(*) begin
    reg_write  = 0;
    alu_src    = 0;
    mem_read   = 0;
    mem_write  = 0;
    mem_to_reg = 0;
    branch=0;
    alu_op     = 2'b00;
    case(opcode)
        7'b0110011: begin //R-type ADD
            reg_write  = 1;
            alu_src    = 0;
            alu_op     = 2'b10;
        end
        7'b0010011: begin //I-type ADDI
            reg_write  = 1;
            alu_src    = 1;
            alu_op     = 2'b00; //force add
        end
        7'b0000011: begin // Load (LW)
            reg_write  = 1;
            mem_read   = 1;
            mem_to_reg = 1; 
            alu_src    = 1;
            mem_write = 0;
            alu_op     = 2'b00;
        end

        7'b0100011: begin // Store (SW)
            reg_write  = 0;
            mem_write   = 1;
            mem_read = 0;
            mem_to_reg = 0; 
            alu_src    = 1;
            alu_op     = 2'b00;
        end
        7'b1100011: begin // BEQ
            reg_write  = 0;
            alu_src    = 0;
            mem_read   = 0;
            mem_write  = 0;
            mem_to_reg = 0;
            branch     = 1;
            alu_op     = 2'b01; // subtract rs1 - rs2
        end

        
        default: begin
            
        end
        endcase
    end

endmodule

src/instruction_mem.v
module instruction_mem (
    input  [31:0] addr, //From PC
    output [31:0] instruction //To Control/Reg
);

    reg [31:0] memory [0:1023];
    
    initial begin
        $readmemh("sample_program.hex", memory);
    end

    assign instruction = memory[addr >> 2]; //converts from the address to the word index, 32 bit so each is 4 bytes

endmodule

src/pc.v
module pc(
    input clk,
    input reset,
    input [31:0] pc_in,
    output reg [31:0] pc_out
);

always @(posedge clk) begin
    if (reset) begin
        pc_out <= 32'b0;
    end else begin
        pc_out <= pc_in;
    end
end
endmodule

src/riscv_top.v
module riscv_top(
    input clk,
    input rst
);
    
    //Internal Wires
    wire [31:0] pc_out, instr;
    wire [31:0] reg_data1, reg_data2, write_data;
    wire [31:0] alu_result, read_data;
    wire [31:0] imm_ext;
    wire [31:0] alu_src2_mux;
    wire [31:0] pc_plus4, branch_target, pc_next;
    wire zero;
    
    //Control Signals
    wire reg_write, alu_src, mem_read, mem_write, mem_to_reg, branch;
    wire [1:0] alu_op;

    //Instruction Slicing
    wire [6:0]  opcode   = instr[6:0];
    wire [4:0]  rd       = instr[11:7];
    wire [2:0]  funct3   = instr[14:12];
    wire [4:0]  sr1      = instr[19:15];
    wire [4:0]  sr2      = instr[24:20];
    wire [6:0]  funct7   = instr[31:25];

    wire is_beq = (opcode == 7'b1100011) && (funct3 == 3'b000);

    // Sign extension for I/S/B types
    wire [31:0] i_ext = {{20{instr[31]}}, instr[31:20]};
    wire [31:0] s_ext = {{20{instr[31]}}, instr[31:25], instr[11:7]};
    wire [31:0] b_ext = {{19{instr[31]}}, instr[31], instr[7], instr[30:25], instr[11:8], 1'b0};
    assign imm_ext = (opcode == 7'b0000011 || opcode == 7'b0010011) ? i_ext : // LW or ADDI
                     (opcode == 7'b0100011) ? s_ext : // SW
                     (opcode == 7'b1100011) ? b_ext : // BEQ
                     32'b0;
    assign pc_plus4      = pc_out + 32'd4;
    assign branch_target = pc_out + imm_ext;
    assign pc_next       = (branch && is_beq && zero) ? branch_target : pc_plus4;

    pc my_pc (
        .clk(clk),
        .reset(rst),
        .pc_in(pc_next),
        .pc_out(pc_out)
    );

    instruction_mem my_imem (
        .addr(pc_out),
        .instruction(instr)
    );

    control_unit my_cu (
        .opcode(opcode),
        .reg_write(reg_write),
        .alu_src(alu_src),
        .mem_read(mem_read),
        .mem_write(mem_write),
        .mem_to_reg(mem_to_reg),
        .alu_op(alu_op),
        .branch(branch)
    );

    reg_file my_regfile (
        .clk(clk),
        .rst(rst),
        .rg_write_en(reg_write),
        .rg_des_addr(rd),
        .rg_sr1_addr(sr1),
        .rg_sr2_addr(sr2),
        .rg_des_data(write_data),
        .rg_sr1_data(reg_data1),
        .rg_sr2_data(reg_data2)
    );

    reg [3:0] alu_control_signal;
    always @(*)begin
        case(alu_op)
            2'b00: alu_control_signal = 4'b0000; // ADD for Load/Store
            2'b01: alu_control_signal = 4'b0001; // SUB for Branch
            2'b10: begin
                case(funct3)
                    3'b000: alu_control_signal = (funct7[5]) ? 4'b0001 : 4'b0000; // SUB or ADD
                    3'b111: alu_control_signal = 4'b0010; // AND
                    3'b110: alu_control_signal = 4'b0011; // OR
                endcase
            end
            default: alu_control_signal = 4'b0000;
        endcase
    end


    alu my_alu(
        .opcode(alu_control_signal),
        .a(reg_data1),
        .b(alu_src2_mux),
        .result(alu_result),
        .zero(zero)
    );

    data_mem my_dmem(
    .clk(clk),
    .mem_read(mem_read),
    .mem_write(mem_write),
    .addr(alu_result),
    .write_data(reg_data2),
    .read_data(read_data)
);
    
    assign alu_src2_mux = (alu_src) ? imm_ext : reg_data2;

    assign write_data = (mem_to_reg) ? read_data : alu_result;

endmodule

test/top_tb.v
`timescale 1ns/1ps

module riscv_top_tb();
    reg clk;
    reg rst;

    riscv_top dut (
        .clk(clk),
        .rst(rst)
    );

    always #5 clk = ~clk;

    initial begin
        $dumpfile("riscv_processor.vcd");
        $dumpvars(0, riscv_top_tb);

        clk = 0;
        rst = 1;
        #15;
        rst = 0;

        // Wait long enough for the BEQ test program to execute.
        #80;

        if (dut.my_regfile.registers[1] !== 32'd5) begin
            $display("FAIL: x1 expected 5, got %0d", dut.my_regfile.registers[1]);
            $finish;
        end

        if (dut.my_regfile.registers[2] !== 32'd5) begin
            $display("FAIL: x2 expected 5, got %0d", dut.my_regfile.registers[2]);
            $finish;
        end

        if (dut.my_regfile.registers[3] !== 32'd0) begin
            $display("FAIL: x3 expected 0 because BEQ should skip ADDI, got %0d", dut.my_regfile.registers[3]);
            $finish;
        end

        if (dut.my_regfile.registers[4] !== 32'd42) begin
            $display("FAIL: x4 expected 42, got %0d", dut.my_regfile.registers[4]);
            $finish;
        end

        $display("PASS: BEQ skipped the ADDI to x3 and executed the ADDI to x4.");
        $finish;
    end
endmodule

riscv_processor.vcd
$date
	Thu Mar 26 16:41:02 2026
$end
$version
	Icarus Verilog
$end
$timescale
	1ps
$end
$scope module riscv_top_tb $end
$var reg 1 ! clk $end
$var reg 1 " rst $end
$scope module dut $end
$var wire 1 ! clk $end
$var wire 1 # is_beq $end
$var wire 1 " rst $end
$var wire 1 $ zero $end
$var wire 32 % write_data [31:0] $end
$var wire 5 & sr2 [4:0] $end
$var wire 5 ' sr1 [4:0] $end
$var wire 32 ( s_ext [31:0] $end
$var wire 1 ) reg_write $end
$var wire 32 * reg_data2 [31:0] $end
$var wire 32 + reg_data1 [31:0] $end
$var wire 32 , read_data [31:0] $end
$var wire 5 - rd [4:0] $end
$var wire 32 . pc_plus4 [31:0] $end
$var wire 32 / pc_out [31:0] $end
$var wire 32 0 pc_next [31:0] $end
$var wire 7 1 opcode [6:0] $end
$var wire 1 2 mem_write $end
$var wire 1 3 mem_to_reg $end
$var wire 1 4 mem_read $end
$var wire 32 5 instr [31:0] $end
$var wire 32 6 imm_ext [31:0] $end
$var wire 32 7 i_ext [31:0] $end
$var wire 7 8 funct7 [6:0] $end
$var wire 3 9 funct3 [2:0] $end
$var wire 32 : branch_target [31:0] $end
$var wire 1 ; branch $end
$var wire 32 < b_ext [31:0] $end
$var wire 32 = alu_src2_mux [31:0] $end
$var wire 1 > alu_src $end
$var wire 32 ? alu_result [31:0] $end
$var wire 2 @ alu_op [1:0] $end
$var reg 4 A alu_control_signal [3:0] $end
$scope module my_alu $end
$var wire 32 B b [31:0] $end
$var wire 4 C opcode [3:0] $end
$var wire 1 $ zero $end
$var wire 32 D a [31:0] $end
$var reg 32 E result [31:0] $end
$upscope $end
$scope module my_cu $end
$var wire 7 F opcode [6:0] $end
$var reg 2 G alu_op [1:0] $end
$var reg 1 > alu_src $end
$var reg 1 ; branch $end
$var reg 1 4 mem_read $end
$var reg 1 3 mem_to_reg $end
$var reg 1 2 mem_write $end
$var reg 1 ) reg_write $end
$upscope $end
$scope module my_dmem $end
$var wire 32 H addr [31:0] $end
$var wire 1 ! clk $end
$var wire 1 4 mem_read $end
$var wire 1 2 mem_write $end
$var wire 32 I write_data [31:0] $end
$var wire 32 J read_data [31:0] $end
$upscope $end
$scope module my_imem $end
$var wire 32 K instruction [31:0] $end
$var wire 32 L addr [31:0] $end
$upscope $end
$scope module my_pc $end
$var wire 1 ! clk $end
$var wire 32 M pc_in [31:0] $end
$var wire 1 " reset $end
$var reg 32 N pc_out [31:0] $end
$upscope $end
$scope module my_regfile $end
$var wire 1 ! clk $end
$var wire 5 O rg_des_addr [4:0] $end
$var wire 32 P rg_des_data [31:0] $end
$var wire 5 Q rg_sr1_addr [4:0] $end
$var wire 5 R rg_sr2_addr [4:0] $end
$var wire 1 ) rg_write_en $end
$var wire 1 " rst $end
$var wire 32 S rg_sr2_data [31:0] $end
$var wire 32 T rg_sr1_data [31:0] $end
$var integer 32 U i [31:0] $end
$upscope $end
$upscope $end
$upscope $end
$enddefinitions $end
$comment Show the parameter values. $end
$dumpall
$end
#0
$dumpvars
bx U
bx T
bx S
bx R
bx Q
bx P
bx O
bx N
bx M
bx L
bx K
bx J
bx I
bx H
bx G
bx F
bx E
bx D
bx C
bx B
bx A
bx @
bx ?
x>
bx =
bx0 <
x;
bx :
bx 9
bx 8
bx 7
bx 6
bx 5
x4
x3
x2
bx 1
bx 0
bx /
bx .
bx -
bx ,
bx +
bx *
x)
bx (
bx '
bx &
bx %
x$
x#
1"
0!
$end
#5000
b101 %
b101 P
0$
b101 ?
b101 E
b101 H
b100 0
b100 M
b101 =
b101 B
b100000000000 <
b101 :
b101 6
b0 ,
b0 J
b1 (
b101 7
b0 *
b0 I
b0 S
b0 +
b0 D
b0 T
b0 A
b0 C
0#
b0 @
b0 G
0;
03
02
04
1>
1)
b0 8
b101 &
b101 R
b0 '
b0 Q
b0 9
b1 -
b1 O
b10011 1
b10011 F
b10100000000000010010011 5
b10100000000000010010011 K
b100 .
b0 /
b0 L
b0 N
b100000 U
1!
#10000
0!
#15000
b10 <
b10 (
b10 -
b10 O
b10100000000000100010011 5
b10100000000000100010011 K
b1000 0
b1000 M
b1001 :
b1000 .
b100 /
b100 L
b100 N
1!
0"
#20000
0!
#25000
b0 %
b0 P
1$
b0 ?
b0 E
b0 H
b1000 <
b101 *
b101 I
b101 S
b1000 6
b1 A
b1 C
b101 =
b101 B
b1000 (
b10 7
b101 +
b101 D
b101 T
1#
b1 @
b1 G
1;
0>
0)
b10 &
b10 R
b1 '
b1 Q
b1000 -
b1000 O
b1100011 1
b1100011 F
b1000001000010001100011 5
b1000001000010001100011 K
b10000 0
b10000 M
b10000 :
b1100 .
b1000 /
b1000 L
b1000 N
1!
#30000
0!
#35000
b101010 %
b101010 P
b100100 <
b0 *
b0 I
b0 S
0$
b101010 ?
b101010 E
b101010 H
b101010 6
b101010 =
b101010 B
b100100 (
b101010 7
b0 A
b0 C
b0 +
b0 D
b0 T
0#
1>
1)
b0 @
b0 G
0;
b1 8
b1010 &
b1010 R
b0 '
b0 Q
b100 -
b100 O
b10011 1
b10011 F
b10101000000000001000010011 5
b10101000000000001000010011 K
b10100 0
b10100 M
b111010 :
b10100 .
b10000 /
b10000 L
b10000 N
1!
#40000
0!
#45000
bx %
bx P
bx0 <
x$
bx ?
bx E
bx H
bx 6
bx =
bx B
bx (
bx 7
bx *
bx I
bx S
bx +
bx D
bx T
x#
0>
0)
bx 8
bx &
bx R
bx '
bx Q
bx 9
bx -
bx O
bx 1
bx F
bx 5
bx K
b11000 0
b11000 M
bx :
b11000 .
b10100 /
b10100 L
b10100 N
1!
#50000
0!
#55000
b11100 0
b11100 M
b11100 .
b11000 /
b11000 L
b11000 N
1!
#60000
0!
#65000
b100000 0
b100000 M
b100000 .
b11100 /
b11100 L
b11100 N
1!
#70000
0!
#75000
b100100 0
b100100 M
b100100 .
b100000 /
b100000 L
b100000 N
1!
#80000
0!
#85000
b101000 0
b101000 M
b101000 .
b100100 /
b100100 L
b100100 N
1!
#90000
0!
#95000
b101100 0
b101100 M
b101100 .
b101000 /
b101000 L
b101000 N
1!
