src/data_mem.v
module data_mem(
    input clk,
    input mem_read,
    input mem_write,
    input [31:0] addr,
    input [31:0] write_data,
    output [31:0] read_data
);

    reg [31:0] memory [0:1023];

    always @(posedge clk) begin
        if (mem_write) begin
            memory[addr[11:2]] <= write_data;
        end
    end

    assign read_data = (mem_read) ? memory[addr[11:2]] : 32'b0;

endmodule

src/alu.v
module alu (
    input [31:0] a,
    input [31:0] b,
    input [3:0] opcode,
    output reg [31:0] result,
    output wire zero 

);
    always @(*) begin
        case (opcode)
            4'b0000: result = a + b; //add
            4'b0001: result = a - b; //sub
            4'b0010: result = a & b; //and
            4'b0011: result = a | b; //or
            
            //discarded for now
            /*4'b0100: result = a ^ b; //xor
            4'b0101: result = ~(a | b); //nor
            4'b0110: result = ~(a & b); //nand
            4'b0111: result = (a<b) ? 32'd1 : 32'd0; //set less than
            4'b1000: result = a << b[4:0]; //shift left logical
            4'b1001: result = a >> b[4:0]; //shift right logical*/
            default: result = 32'b0; 
        endcase
    end

    assign zero = (result == 32'b0);

endmodule

src/register_file.v
module reg_file (
    input clk,
    input rst,
    input rg_write_en,// Write Enable: only write if this is 1
    input [4:0] rg_des_addr,// Destination register index (0-31)
    input [4:0] rg_sr1_addr,// Source 1 register index (0-31)
    input [4:0] rg_sr2_addr,// Source 2 register index (0-31)
    input [31:0] rg_des_data,// Data to be written
    output [31:0] rg_sr1_data,// Data read from Source 1
    output [31:0] rg_sr2_data// Data read from Source 2
);
reg [31:0] registers [31:0];
integer i;

assign rg_sr1_data = (rg_sr1_addr == 5'b0) ? 32'b0 : registers[rg_sr1_addr];
assign rg_sr2_data = (rg_sr2_addr == 5'b0) ? 32'b0 : registers[rg_sr2_addr];

always @(posedge clk) begin
    if(rst) begin
        for(i=0;  i<32; i=i+1)begin
            registers[i] <=32'b0;
        end
    end 
    else if (rg_write_en && (rg_des_addr!=5'b0)) begin
            registers[rg_des_addr] <= rg_des_data;
    end
end



endmodule

src/control_unit.v
module control_unit(
    input [6:0] opcode,
    output reg reg_write,
    output reg alu_src,
    output reg mem_read,
    output reg mem_write,
    output reg mem_to_reg,
    output reg [1:0] alu_op

);
always @(*) begin
    reg_write  = 0;
    alu_src    = 0;
    mem_read   = 0;
    mem_write  = 0;
    mem_to_reg = 0;
    alu_op     = 2'b00;
    case(opcode)
        7'b0110011: begin //R-type ADD
            reg_write  = 1;
            alu_src    = 0;
            alu_op     = 2'b10;
        end
        7'b0010011: begin //I-type ADDI
            reg_write  = 1;
            alu_src    = 1;
            alu_op     = 2'b00; //force add
        end
        7'b0000011: begin // Load (LW)
            reg_write  = 1;
            mem_read   = 1;
            mem_to_reg = 1; 
            alu_src    = 1;
            mem_write = 0;
            alu_op     = 2'b00;
        end

        7'b0100011: begin // Store (SW)
            reg_write  = 0;
            mem_write   = 1;
            mem_read = 0;
            mem_to_reg = 0; 
            alu_src    = 1;
            alu_op     = 2'b00;
        end
        
        default: begin
            
        end
        endcase
    end

endmodule

src/instruction_mem.v
module instruction_mem (
    input  [31:0] addr, //From PC
    output [31:0] instruction //To Control/Reg
);

    reg [31:0] memory [0:1023];
    
    initial begin
        $readmemh("sample_program.hex", memory);
    end

    assign instruction = memory[addr >> 2]; //converts from the address to the word index

endmodule

src/pc.v
module pc(
    input clk,
    input reset,
    //input [31:0] pc_in,
    output reg [31:0] pc_out
);

always @(posedge clk) begin
    if (reset) begin
        pc_out <= 32'b0;
    end else begin
        pc_out <= pc_out+4;
    end
end
endmodule

src/riscv_top.v
module riscv_top(
    input clk,
    input rst
);

    //Internal Wires
    wire [31:0] pc_out, instr;
    wire [31:0] reg_data1, reg_data2, write_data;
    wire [31:0] alu_result, read_data;
    wire [31:0] imm_ext;
    wire [31:0] alu_src2_mux;
    
    //Control Signals
    wire reg_write, alu_src, mem_read, mem_write, mem_to_reg;
    wire [1:0] alu_op;

    //Instruction Slicing
    wire [6:0]  opcode   = instr[6:0];
    wire [4:0]  rd       = instr[11:7];
    wire [2:0]  funct3   = instr[14:12];
    wire [4:0]  sr1      = instr[19:15];
    wire [4:0]  sr2      = instr[24:20];
    wire [6:0]  funct7   = instr[31:25];

    //Sign extension for I type
    wire [31:0] i_ext = {{20{instr[31]}}, instr[31:20]};
    wire [31:0] s_ext = {{20{instr[31]}}, instr[31:25], instr[11:7]};
    assign imm_ext = (opcode == 7'b0000011 || opcode == 7'b0010011) ? i_ext : // LW or ADDI
                     (opcode == 7'b0100011) ? s_ext : 32'b0; // SW

    pc my_pc (
        .clk(clk),
        .reset(rst),
        .pc_out(pc_out)
    );

    instruction_mem my_imem (
        .addr(pc_out),
        .instruction(instr)
    );

    control_unit my_cu (
        .opcode(opcode),
        .reg_write(reg_write),
        .alu_src(alu_src),
        .mem_read(mem_read),
        .mem_write(mem_write),
        .mem_to_reg(mem_to_reg),
        .alu_op(alu_op)
    );

    reg_file my_regfile (
        .clk(clk),
        .rst(rst),
        .rg_write_en(reg_write),
        .rg_des_addr(rd),
        .rg_sr1_addr(sr1),
        .rg_sr2_addr(sr2),
        .rg_des_data(write_data),
        .rg_sr1_data(reg_data1),
        .rg_sr2_data(reg_data2)
    );

    reg [3:0] alu_control_signal;
    always @(*)begin
        case(alu_op)
            2'b00: alu_control_signal = 4'b0000; // ADD for Load/Store
            2'b01: alu_control_signal = 4'b0001; // SUB for Branch
            2'b10: begin
                case(funct3)
                    3'b000: alu_control_signal = (funct7[5]) ? 4'b0001 : 4'b0000; // SUB or ADD
                    3'b111: alu_control_signal = 4'b0010; // AND
                    3'b110: alu_control_signal = 4'b0011; // OR
                endcase
            end
            default: alu_control_signal = 4'b0000;
        endcase
    end


    alu my_alu(
        .opcode(alu_control_signal),
        .a(reg_data1),
        .b(alu_src2_mux),
        .result(alu_result)
    );

    data_mem my_dmem(
    .clk(clk),
    .mem_read(mem_read),
    .mem_write(mem_write),
    .addr(alu_result),
    .write_data(reg_data2),
    .read_data(read_data)
);
    
    assign alu_src2_mux = (alu_src) ? imm_ext : reg_data2;

    assign write_data = (mem_to_reg) ? read_data : alu_result;

endmodule

test/top_tb.v
`timescale 1ns/1ps

module riscv_top_tb();
    reg clk;
    reg rst;

    riscv_top dut (
        .clk(clk),
        .rst(rst)
    );

    always #5 clk = ~clk;

    initial begin
        $dumpfile("riscv_processor.vcd");
        $dumpvars(0, riscv_top_tb);

        clk = 0;
        rst = 1;
        #15;
        rst = 0;
        #1000;

        $display("Simulation finished. Open riscv_processor.vcd in GTKWave.");
        $finish;
    end
endmodule

sim/riscv_processor.vcd
$date
	Tue Jan 20 16:25:52 2026
$end
$version
	Icarus Verilog
$end
$timescale
	1ps
$end
$scope module riscv_top_tb $end
$var reg 1 ! clk $end
$var reg 1 " rst $end
$scope module dut $end
$var wire 1 ! clk $end
$var wire 1 " rst $end
$var wire 32 # write_data [31:0] $end
$var wire 5 $ sr2 [4:0] $end
$var wire 5 % sr1 [4:0] $end
$var wire 32 & s_ext [31:0] $end
$var wire 1 ' reg_write $end
$var wire 32 ( reg_data2 [31:0] $end
$var wire 32 ) reg_data1 [31:0] $end
$var wire 32 * read_data [31:0] $end
$var wire 5 + rd [4:0] $end
$var wire 32 , pc_out [31:0] $end
$var wire 7 - opcode [6:0] $end
$var wire 1 . mem_write $end
$var wire 1 / mem_to_reg $end
$var wire 1 0 mem_read $end
$var wire 32 1 instr [31:0] $end
$var wire 32 2 imm_ext [31:0] $end
$var wire 32 3 i_ext [31:0] $end
$var wire 7 4 funct7 [6:0] $end
$var wire 3 5 funct3 [2:0] $end
$var wire 32 6 alu_src2_mux [31:0] $end
$var wire 1 7 alu_src $end
$var wire 32 8 alu_result [31:0] $end
$var wire 2 9 alu_op [1:0] $end
$var reg 4 : alu_control_signal [3:0] $end
$scope module my_alu $end
$var wire 32 ; b [31:0] $end
$var wire 4 < opcode [3:0] $end
$var wire 1 = zero $end
$var wire 32 > a [31:0] $end
$var reg 32 ? result [31:0] $end
$upscope $end
$scope module my_cu $end
$var wire 7 @ opcode [6:0] $end
$var reg 2 A alu_op [1:0] $end
$var reg 1 7 alu_src $end
$var reg 1 0 mem_read $end
$var reg 1 / mem_to_reg $end
$var reg 1 . mem_write $end
$var reg 1 ' reg_write $end
$upscope $end
$scope module my_dmem $end
$var wire 32 B addr [31:0] $end
$var wire 1 ! clk $end
$var wire 1 0 mem_read $end
$var wire 1 . mem_write $end
$var wire 32 C write_data [31:0] $end
$var wire 32 D read_data [31:0] $end
$upscope $end
$scope module my_imem $end
$var wire 32 E instruction [31:0] $end
$var wire 32 F addr [31:0] $end
$upscope $end
$scope module my_pc $end
$var wire 1 ! clk $end
$var wire 1 " reset $end
$var reg 32 G pc_out [31:0] $end
$upscope $end
$scope module my_regfile $end
$var wire 1 ! clk $end
$var wire 5 H rg_des_addr [4:0] $end
$var wire 32 I rg_des_data [31:0] $end
$var wire 5 J rg_sr1_addr [4:0] $end
$var wire 5 K rg_sr2_addr [4:0] $end
$var wire 1 ' rg_write_en $end
$var wire 1 " rst $end
$var wire 32 L rg_sr2_data [31:0] $end
$var wire 32 M rg_sr1_data [31:0] $end
$var integer 32 N i [31:0] $end
$upscope $end
$upscope $end
$upscope $end
$enddefinitions $end
$comment Show the parameter values. $end
$dumpall
$end
#0
$dumpvars
bx N
bx M
bx L
bx K
bx J
bx I
bx H
bx G
bx F
bx E
bx D
bx C
bx B
bx A
bx @
bx ?
bx >
x=
bx <
bx ;
bx :
bx 9
bx 8
x7
bx 6
bx 5
bx 4
bx 3
bx 2
bx 1
x0
x/
x.
bx -
bx ,
bx +
bx *
bx )
bx (
x'
bx &
bx %
bx $
bx #
1"
0!
$end
#5000
b101 #
b101 I
0=
b101 8
b101 ?
b101 B
b101 6
b101 ;
b101 2
b0 *
b0 D
b1 &
b101 3
b0 (
b0 C
b0 L
b0 )
b0 >
b0 M
b0 :
b0 <
b0 9
b0 A
0/
0.
00
17
1'
b0 4
b101 $
b101 K
b0 %
b0 J
b0 5
b1 +
b1 H
b10011 -
b10011 @
b10100000000000010010011 1
b10100000000000010010011 E
b0 ,
b0 F
b0 G
b100000 N
1!
#10000
0!
#15000
b1010 #
b1010 I
b1010 8
b1010 ?
b1010 B
b1010 6
b1010 ;
b1010 2
b10 &
b1010 3
b1010 $
b1010 K
b10 +
b10 H
b101000000000000100010011 1
b101000000000000100010011 E
b100 ,
b100 F
b100 G
1!
0"
#20000
0!
#25000
b1111 #
b1111 I
b1010 (
b1010 C
b1010 L
b1111 8
b1111 ?
b1111 B
b0 2
b1010 6
b1010 ;
b11 &
b10 3
b101 )
b101 >
b101 M
b10 9
b10 A
07
1'
b10 $
b10 K
b1 %
b1 J
b11 +
b11 H
b110011 -
b110011 @
b1000001000000110110011 1
b1000001000000110110011 E
b1000 ,
b1000 F
b1000 G
1!
#30000
0!
#35000
b1010 #
b1010 I
b1010 8
b1010 ?
b1010 B
b1111 (
b1111 C
b1111 L
b1010 )
b1010 >
b1010 M
b0 2
b0 6
b0 ;
b0 &
b11 3
17
1.
b0 9
b0 A
0'
b11 $
b11 K
b10 %
b10 J
b10 5
b0 +
b0 H
b100011 -
b100011 @
b1100010010000000100011 1
b1100010010000000100011 E
b1100 ,
b1100 F
b1100 G
1!
#40000
0!
#45000
b1010 6
b1010 ;
b0 (
b0 C
b0 L
0=
b1010 8
b1010 ?
b1010 B
b1010 2
b1111 #
b1111 I
b1111 *
b1111 D
b100 &
b1010 3
b0 )
b0 >
b0 M
1/
10
1'
0.
17
b1010 $
b1010 K
b0 %
b0 J
b100 +
b100 H
b11 -
b11 @
b101000000010001000000011 1
b101000000010001000000011 E
b10000 ,
b10000 F
b10000 G
1!
#50000
0!
#55000
x=
bx 8
bx ?
bx B
bx 2
bx #
bx I
b0 *
b0 D
bx 6
bx ;
bx &
bx 3
bx (
bx C
bx L
bx )
bx >
bx M
0/
00
07
0'
bx 4
bx $
bx K
bx %
bx J
bx 5
bx +
bx H
bx -
bx @
bx 1
bx E
b10100 ,
b10100 F
b10100 G
1!
#60000
0!
#65000
b11000 ,
b11000 F
b11000 G
1!
#70000
0!
#75000
b11100 ,
b11100 F
b11100 G
1!
#80000
0!
#85000
b100000 ,
b100000 F
b100000 G
1!
#90000
0!
#95000
b100100 ,
b100100 F
b100100 G
1!
#100000
0!
#105000
b101000 ,
b101000 F
b101000 G
1!
#110000
0!
#115000
b101100 ,
b101100 F
b101100 G
1!
#120000
0!
#125000
b110000 ,
b110000 F
b110000 G
1!
#130000
0!
#135000
b110100 ,
b110100 F
b110100 G
1!
#140000
0!
#145000
b111000 ,
b111000 F
b111000 G
1!
#150000
0!
#155000
b111100 ,
b111100 F
b111100 G
1!
#160000
0!
#165000
b1000000 ,
b1000000 F
b1000000 G
1!
#170000
0!
#175000
b1000100 ,
b1000100 F
b1000100 G
1!
#180000
0!
#185000
b1001000 ,
b1001000 F
b1001000 G
1!
#190000
0!
#195000
b1001100 ,
b1001100 F
b1001100 G
1!
#200000
0!
#205000
b1010000 ,
b1010000 F
b1010000 G
1!
#210000
0!
#215000
b1010100 ,
b1010100 F
b1010100 G
1!
#220000
0!
#225000
b1011000 ,
b1011000 F
b1011000 G
1!
#230000
0!
#235000
b1011100 ,
b1011100 F
b1011100 G
1!
#240000
0!
#245000
b1100000 ,
b1100000 F
b1100000 G
1!
#250000
0!
#255000
b1100100 ,
b1100100 F
b1100100 G
1!
#260000
0!
#265000
b1101000 ,
b1101000 F
b1101000 G
1!
#270000
0!
#275000
b1101100 ,
b1101100 F
b1101100 G
1!
#280000
0!
#285000
b1110000 ,
b1110000 F
b1110000 G
1!
#290000
0!
#295000
b1110100 ,
b1110100 F
b1110100 G
1!
#300000
0!
#305000
b1111000 ,
b1111000 F
b1111000 G
1!
#310000
0!
#315000
b1111100 ,
b1111100 F
b1111100 G
1!
#320000
0!
#325000
b10000000 ,
b10000000 F
b10000000 G
1!
#330000
0!
#335000
b10000100 ,
b10000100 F
b10000100 G
1!
#340000
0!
#345000
b10001000 ,
b10001000 F
b10001000 G
1!
#350000
0!
#355000
b10001100 ,
b10001100 F
b10001100 G
1!
#360000
0!
#365000
b10010000 ,
b10010000 F
b10010000 G
1!
#370000
0!
#375000
b10010100 ,
b10010100 F
b10010100 G
1!
#380000
0!
#385000
b10011000 ,
b10011000 F
b10011000 G
1!
#390000
0!
#395000
b10011100 ,
b10011100 F
b10011100 G
1!
#400000
0!
#405000
b10100000 ,
b10100000 F
b10100000 G
1!
#410000
0!
#415000
b10100100 ,
b10100100 F
b10100100 G
1!
#420000
0!
#425000
b10101000 ,
b10101000 F
b10101000 G
1!
#430000
0!
#435000
b10101100 ,
b10101100 F
b10101100 G
1!
#440000
0!
#445000
b10110000 ,
b10110000 F
b10110000 G
1!
#450000
0!
#455000
b10110100 ,
b10110100 F
b10110100 G
1!
#460000
0!
#465000
b10111000 ,
b10111000 F
b10111000 G
1!
#470000
0!
#475000
b10111100 ,
b10111100 F
b10111100 G
1!
#480000
0!
#485000
b11000000 ,
b11000000 F
b11000000 G
1!
#490000
0!
#495000
b11000100 ,
b11000100 F
b11000100 G
1!
#500000
0!
#505000
b11001000 ,
b11001000 F
b11001000 G
1!
#510000
0!
#515000
b11001100 ,
b11001100 F
b11001100 G
1!
#520000
0!
#525000
b11010000 ,
b11010000 F
b11010000 G
1!
#530000
0!
#535000
b11010100 ,
b11010100 F
b11010100 G
1!
#540000
0!
#545000
b11011000 ,
b11011000 F
b11011000 G
1!
#550000
0!
#555000
b11011100 ,
b11011100 F
b11011100 G
1!
#560000
0!
#565000
b11100000 ,
b11100000 F
b11100000 G
1!
#570000
0!
#575000
b11100100 ,
b11100100 F
b11100100 G
1!
#580000
0!
#585000
b11101000 ,
b11101000 F
b11101000 G
1!
#590000
0!
#595000
b11101100 ,
b11101100 F
b11101100 G
1!
#600000
0!
#605000
b11110000 ,
b11110000 F
b11110000 G
1!
#610000
0!
#615000
b11110100 ,
b11110100 F
b11110100 G
1!
#620000
0!
#625000
b11111000 ,
b11111000 F
b11111000 G
1!
#630000
0!
#635000
b11111100 ,
b11111100 F
b11111100 G
1!
#640000
0!
#645000
b100000000 ,
b100000000 F
b100000000 G
1!
#650000
0!
#655000
b100000100 ,
b100000100 F
b100000100 G
1!
#660000
0!
#665000
b100001000 ,
b100001000 F
b100001000 G
1!
#670000
0!
#675000
b100001100 ,
b100001100 F
b100001100 G
1!
#680000
0!
#685000
b100010000 ,
b100010000 F
b100010000 G
1!
#690000
0!
#695000
b100010100 ,
b100010100 F
b100010100 G
1!
#700000
0!
#705000
b100011000 ,
b100011000 F
b100011000 G
1!
#710000
0!
#715000
b100011100 ,
b100011100 F
b100011100 G
1!
#720000
0!
#725000
b100100000 ,
b100100000 F
b100100000 G
1!
#730000
0!
#735000
b100100100 ,
b100100100 F
b100100100 G
1!
#740000
0!
#745000
b100101000 ,
b100101000 F
b100101000 G
1!
#750000
0!
#755000
b100101100 ,
b100101100 F
b100101100 G
1!
#760000
0!
#765000
b100110000 ,
b100110000 F
b100110000 G
1!
#770000
0!
#775000
b100110100 ,
b100110100 F
b100110100 G
1!
#780000
0!
#785000
b100111000 ,
b100111000 F
b100111000 G
1!
#790000
0!
#795000
b100111100 ,
b100111100 F
b100111100 G
1!
#800000
0!
#805000
b101000000 ,
b101000000 F
b101000000 G
1!
#810000
0!
#815000
b101000100 ,
b101000100 F
b101000100 G
1!
#820000
0!
#825000
b101001000 ,
b101001000 F
b101001000 G
1!
#830000
0!
#835000
b101001100 ,
b101001100 F
b101001100 G
1!
#840000
0!
#845000
b101010000 ,
b101010000 F
b101010000 G
1!
#850000
0!
#855000
b101010100 ,
b101010100 F
b101010100 G
1!
#860000
0!
#865000
b101011000 ,
b101011000 F
b101011000 G
1!
#870000
0!
#875000
b101011100 ,
b101011100 F
b101011100 G
1!
#880000
0!
#885000
b101100000 ,
b101100000 F
b101100000 G
1!
#890000
0!
#895000
b101100100 ,
b101100100 F
b101100100 G
1!
#900000
0!
#905000
b101101000 ,
b101101000 F
b101101000 G
1!
#910000
0!
#915000
b101101100 ,
b101101100 F
b101101100 G
1!
#920000
0!
#925000
b101110000 ,
b101110000 F
b101110000 G
1!
#930000
0!
#935000
b101110100 ,
b101110100 F
b101110100 G
1!
#940000
0!
#945000
b101111000 ,
b101111000 F
b101111000 G
1!
#950000
0!
#955000
b101111100 ,
b101111100 F
b101111100 G
1!
#960000
0!
#965000
b110000000 ,
b110000000 F
b110000000 G
1!
#970000
0!
#975000
b110000100 ,
b110000100 F
b110000100 G
1!
#980000
0!
#985000
b110001000 ,
b110001000 F
b110001000 G
1!
#990000
0!
#995000
b110001100 ,
b110001100 F
b110001100 G
1!
#1000000
0!
#1005000
b110010000 ,
b110010000 F
b110010000 G
1!
#1010000
0!
#1015000
b110010100 ,
b110010100 F
b110010100 G
1!
